{
  "project_info": {
    "project_number": "109501654602",
    "project_id": "fyp1-d83cc",
    "storage_bucket": "fyp1-d83cc.appspot.com"
  },
  "client": [
    {
      "client_info": {
        "mobilesdk_app_id": "1:109501654602:android:c690b2066d655c2f0128b3",
        "android_client_info": {
          "package_name": "com.example.abcd"
        }
      },
      "oauth_client": [
        {
          "client_id": "109501654602-l07evll50e1507g8c1i21fotmsj60lu4.apps.googleusercontent.com",
          "client_type": 3
        }
      ],
      "api_key": [
        {
          "current_key": "AIzaSyAxAr3UewNBb1jHXZ0V28AAZYjSmunBRFg"
        }
      ],
      "services": {
        "appinvite_service": {
          "other_platform_oauth_client": [
            {
              "client_id": "109501654602-l07evll50e1507g8c1i21fotmsj60lu4.apps.googleusercontent.com",
              "client_type": 3
            }
          ]
        }
      }
    }
  ],
  "configuration_version": "1"
}